<YealinkIPPhoneDirectory>
  <DirectoryEntry>
    <Name>Abonados/ARAMO</Name>
    <Telephone>803</Telephone>
    <Telephone>229337404</Telephone>
  </DirectoryEntry>
  <DirectoryEntry>
    <Name>Abonados/RG</Name>
    <Telephone>800</Telephone>
  </DirectoryEntry>
  <DirectoryEntry>
    <Name>Abonados/Casa MAO</Name>
    <Telephone>801</Telephone>
  </DirectoryEntry>
  <DirectoryEntry>
    <Name>Abonados/Casa Daniela</Name>
    <Telephone>802</Telephone>
  </DirectoryEntry>
  <DirectoryEntry>
    <Name>Abonados/Lilian Alaluf</Name>
    <Telephone>804</Telephone>
  </DirectoryEntry>
</YealinkIPPhoneDirectory>
