<?xml version="1.0" encoding="utf-8" ?><dwsync><file name="da.php" server="california.tnasolutions.cl//public_html/" local="3729523145" remote="3638750400" Dst="-1" /><file name="de.php" server="california.tnasolutions.cl//public_html/" local="3729523145" remote="3638750400" Dst="-1" /><file name="es.php" server="california.tnasolutions.cl//public_html/" local="3729523145" remote="3638750400" Dst="-1" /><file name="fi.php" server="california.tnasolutions.cl//public_html/" local="3729523145" remote="3638750400" Dst="-1" /><file name="it.php" server="california.tnasolutions.cl//public_html/" local="3729523145" remote="3638750400" Dst="-1" /><file name="pt.php" server="california.tnasolutions.cl//public_html/" local="3729523145" remote="3638750400" Dst="-1" /><file name="ru.php" server="california.tnasolutions.cl//public_html/" local="3729523145" remote="3638750400" Dst="-1" /><file name="sv.php" server="california.tnasolutions.cl//public_html/" local="3729523145" remote="3638750400" Dst="-1" /><file name="sv.php" server="california.icontel.cl//public_html/" local="3729523145" remote="3758204880" Dst="-1" /><file name="ru.php" server="california.icontel.cl//public_html/" local="3729523145" remote="3758204880" Dst="-1" /><file name="es.php" server="california.icontel.cl//public_html/" local="3729523145" remote="3758204880" Dst="-1" /><file name="da.php" server="california.icontel.cl//public_html/" local="3729523145" remote="3758204880" Dst="-1" /><file name="fi.php" server="california.icontel.cl//public_html/" local="3729523145" remote="3758204880" Dst="-1" /><file name="pt.php" server="california.icontel.cl//public_html/" local="3729523145" remote="3758204880" Dst="-1" /><file name="de.php" server="california.icontel.cl//public_html/" local="3729523145" remote="3758204880" Dst="-1" /><file name="it.php" server="california.icontel.cl//public_html/" local="3729523145" remote="3758204880" Dst="-1" /></dwsync>